{"assets":{"3F31FB1C6482085783ED237C5946F3B3":{"type":"texture","index":451,"assetRequest":{"type":"slide","state":"outgoing","slide":"34B399FE-31E3-4346-B6BA-E8BCEA8F1692"},"url":"assets/3F31FB1C6482085783ED237C5946F3B3.svg","width":1024,"height":768},"crrect_answer3.mp3-0.0000-2.4480":{"type":"audio","index":0,"assetRequest":{},"url":"assets/crrect_answer3.mp3-0.0000-2.4480.m4a","width":0,"height":0},"FA4CF99553AC39E60FF2C938B73757CC":{"type":"texture","index":447,"assetRequest":{"type":"slide","state":"contents","slide":"34B399FE-31E3-4346-B6BA-E8BCEA8F1692"},"url":"assets/FA4CF99553AC39E60FF2C938B73757CC.svg","width":1026,"height":770},"8A2C835FC8BD9D135CD739D6C99EC526":{"type":"texture","index":449,"assetRequest":{"type":"slide","state":"contents","slide":"34B399FE-31E3-4346-B6BA-E8BCEA8F1692"},"url":"assets/8A2C835FC8BD9D135CD739D6C99EC526.svg","width":372,"height":371},"57BFB1565B11D17E0D5A3302F4E76C9B":{"type":"texture","index":452,"assetRequest":{"type":"slide","state":"incoming","slide":"556F520D-83B4-4A3D-A31F-A820DC724E09"},"url":"assets/57BFB1565B11D17E0D5A3302F4E76C9B.svg","width":1024,"height":768},"8F6820361D2B1BCD4C02FD502FE51D8F":{"type":"texture","index":448,"assetRequest":{"type":"slide","state":"contents","slide":"34B399FE-31E3-4346-B6BA-E8BCEA8F1692"},"url":"assets/8F6820361D2B1BCD4C02FD502FE51D8F.svg","width":1028,"height":190},"BB5CB91ED7406511BDB06F3E85F7244F":{"type":"texture","index":446,"assetRequest":{"type":"slide","state":"contents","slide":"34B399FE-31E3-4346-B6BA-E8BCEA8F1692"},"url":"assets/BB5CB91ED7406511BDB06F3E85F7244F.svg","width":1024,"height":768},"D7668D704E27AC9557F646207BF431C4":{"type":"texture","index":450,"assetRequest":{"type":"slide","state":"contents","slide":"34B399FE-31E3-4346-B6BA-E8BCEA8F1692"},"url":"assets/D7668D704E27AC9557F646207BF431C4.svg","width":67,"height":72}},"events":[{"effects":[{"objectID":"A665A0D2-967B-4580-ACCD-918970C2370F","effects":[{"beginTime":0,"effects":[],"movie":{"startTime":0,"volume":1,"endTime":2.447999954223633,"isStreaming":false,"isAudioOnly":true,"asset":"crrect_answer3.mp3-0.0000-2.4480"},"duration":0,"type":"none","name":"renderMovie","objectID":"A665A0D2-967B-4580-ACCD-918970C2370F"}],"beginTime":0,"name":"apple:audio-start","type":"buildIn","duration":0.5},{"beginTime":0,"baseLayer":{"animations":[],"initialState":{"affineTransform":[1,0,0,1,0,0],"masksToBounds":false,"rotation":0,"scale":1,"position":{"pointX":512.0000152587891,"pointY":310.2343597412109},"width":356.3009338378906,"sublayerTransform":[1,0,0,0,0,1,0,0,0,0,1,0,0,0,0,1],"contentsRect":{"y":0,"x":0,"width":1,"height":1},"opacity":1,"edgeAntialiasingMask":15,"height":356.3009338378906,"hidden":false,"anchorPoint":{"pointX":0.5,"pointY":0.5}},"objectID":"97EDECDC-5164-4331-8E0F-AB7BB4666B34","layers":[{"animations":[{"repeatCount":0,"animations":[{"from":{"pointX":0.5000000410182501,"pointY":1},"beginTime":0,"repeatCount":0,"fillMode":"removed","property":"anchorPoint","duration":1,"to":{"pointX":0.5000000410182501,"pointY":1}},{"timingFunctions":[{"timingFunction":"linear"},{"timingFunction":"linear"},{"timingFunction":"easeOut"},{"timingFunction":"linear"},{"timingFunction":"linear"},{"timingFunction":"linear"},{"timingFunction":"easeOut"},{"timingFunction":"linear"},{"timingFunction":"linear"},{"timingFunction":"linear"},{"timingFunction":"easeOut"},{"timingFunction":"linear"}],"values":[{"scalar":1},{"scalar":1},{"scalar":1},{"scalar":0.9},{"scalar":1},{"scalar":1},{"scalar":1},{"scalar":0.9333333333333333},{"scalar":1},{"scalar":1},{"scalar":1},{"scalar":0.9666666666666667},{"scalar":1}],"beginTime":0,"repeatCount":0,"keyTimes":[0,0.09999999999999999,0.2333333333333333,0.2833333333333333,0.3333333333333333,0.4333333333333333,0.5666666666666667,0.6166666666666667,0.6666666666666666,0.7666666666666666,0.8999999999999999,0.95,1],"property":"transform.scale.y","fillMode":"forwards","duration":1},{"timingFunctions":[{"timingFunction":"easeOut"},{"timingFunction":"easeIn"},{"timingFunction":"easeOut"},{"timingFunction":"easeIn"},{"timingFunction":"easeOut"},{"timingFunction":"easeIn"},{"timingFunction":"easeOut"},{"timingFunction":"easeIn"},{"timingFunction":"easeOut"},{"timingFunction":"easeIn"},{"timingFunction":"easeOut"},{"timingFunction":"easeIn"}],"values":[{"scalar":185.765640258789},{"scalar":70.56564025878905},{"scalar":185.765640258789},{"scalar":185.765640258789},{"scalar":185.765640258789},{"scalar":108.965640258789},{"scalar":185.765640258789},{"scalar":185.765640258789},{"scalar":185.765640258789},{"scalar":147.365640258789},{"scalar":185.765640258789},{"scalar":185.765640258789},{"scalar":185.765640258789}],"beginTime":0,"repeatCount":0,"keyTimes":[0,0.09999999999999999,0.2333333333333333,0.2833333333333333,0.3333333333333333,0.4333333333333333,0.5666666666666667,0.6166666666666667,0.6666666666666666,0.7666666666666666,0.8999999999999999,0.95,1],"property":"transform.translation.y","fillMode":"forwards","duration":1},{"timingFunctions":[{"timingFunction":"linear"},{"timingFunction":"linear"},{"timingFunction":"easeOut"},{"timingFunction":"linear"},{"timingFunction":"linear"},{"timingFunction":"linear"},{"timingFunction":"easeOut"},{"timingFunction":"linear"},{"timingFunction":"linear"},{"timingFunction":"linear"},{"timingFunction":"easeOut"},{"timingFunction":"linear"}],"values":[{"scalar":1},{"scalar":1},{"scalar":1},{"scalar":1.1},{"scalar":1},{"scalar":1},{"scalar":1},{"scalar":1.066666666666667},{"scalar":1},{"scalar":1},{"scalar":1},{"scalar":1.033333333333333},{"scalar":1}],"beginTime":0,"repeatCount":0,"keyTimes":[0,0.09999999999999999,0.2333333333333333,0.2833333333333333,0.3333333333333333,0.4333333333333333,0.5666666666666667,0.6166666666666667,0.6666666666666666,0.7666666666666666,0.8999999999999999,0.95,1],"property":"transform.scale.x","fillMode":"forwards","duration":1}],"beginTime":1e-100,"fillMode":"both","duration":1}],"layers":[],"initialState":{"affineTransform":[1,0,0,1,0,0],"masksToBounds":false,"rotation":0,"scale":1,"position":{"pointX":178.1504669189453,"pointY":178.1504669189453},"width":372,"sublayerTransform":[1,0,0,0,0,1,0,0,0,0,1,0,0,0,0,1],"contentsRect":{"y":0,"x":0,"width":1,"height":1},"opacity":1,"edgeAntialiasingMask":0,"height":371,"hidden":false,"anchorPoint":{"pointX":0.5000000410182501,"pointY":0.4992839885207842}},"texture":"8A2C835FC8BD9D135CD739D6C99EC526"}]},"effects":[],"duration":1,"type":"actionBuild","name":"apple:action-bounce","objectID":"97EDECDC-5164-4331-8E0F-AB7BB4666B34"}],"automaticPlay":true,"hyperlinks":[{"url":"?slide=next","events":{"556F520D-83B4-4A3D-A31F-A820DC724E09":{"effects":[{"beginTime":0,"baseLayer":{"animations":[],"initialState":{"affineTransform":[1,0,0,1,0,0],"masksToBounds":true,"rotation":0,"scale":1,"position":{"pointX":512,"pointY":384},"width":1024,"sublayerTransform":[1,0,0,0,0,1,0,0,0,0,1,0,0,0,0,1],"contentsRect":{"y":0,"x":0,"width":1,"height":1},"opacity":1,"edgeAntialiasingMask":0,"height":768,"hidden":false,"anchorPoint":{"pointX":0.5,"pointY":0.5}},"objectID":"0","layers":[{"animations":[],"initialState":{"affineTransform":[1,0,0,1,0,0],"masksToBounds":false,"rotation":0,"scale":1,"position":{"pointX":512,"pointY":384},"width":1024,"sublayerTransform":[1,0,0,0,0,1,0,0,0,0,1,-0.0004922987690640373,0,0,0,1],"contentsRect":{"y":0,"x":0,"width":1,"height":1},"opacity":1,"edgeAntialiasingMask":15,"height":768,"hidden":false,"anchorPoint":{"pointX":0.5,"pointY":0.5}},"layers":[{"animations":[],"layers":[],"initialState":{"affineTransform":[1,0,0,1,0,0],"masksToBounds":false,"rotation":0,"scale":1,"position":{"pointX":512,"pointY":384},"width":1024,"sublayerTransform":[1,0,0,0,0,1,0,0,0,0,1,0,0,0,0,1],"contentsRect":{"y":0,"x":0,"width":1,"height":1},"opacity":1,"edgeAntialiasingMask":0,"height":768,"hidden":false,"anchorPoint":{"pointX":0.5,"pointY":0.5}},"texture":"57BFB1565B11D17E0D5A3302F4E76C9B"},{"animations":[{"from":{"scalar":false},"beginTime":0,"repeatCount":0,"fillMode":"both","property":"hidden","duration":0.01,"to":{"scalar":true}}],"layers":[],"initialState":{"affineTransform":[1,0,0,1,0,0],"masksToBounds":false,"rotation":0,"scale":1,"position":{"pointX":512,"pointY":384},"width":1024,"sublayerTransform":[1,0,0,0,0,1,0,0,0,0,1,0,0,0,0,1],"contentsRect":{"y":0,"x":0,"width":1,"height":1},"opacity":1,"edgeAntialiasingMask":0,"height":768,"hidden":false,"anchorPoint":{"pointX":0.5,"pointY":0.5}},"texture":"3F31FB1C6482085783ED237C5946F3B3"}]}]},"effects":[],"duration":0.01,"type":"transition","name":"none","objectID":"0"}],"automaticPlay":false,"hyperlinks":[],"accessibility":[],"baseLayer":{"animations":[],"initialState":{"affineTransform":[1,0,0,1,0,0],"masksToBounds":true,"rotation":0,"scale":1,"position":{"pointX":512,"pointY":384},"width":1024,"sublayerTransform":[1,0,0,0,0,1,0,0,0,0,1,0,0,0,0,1],"contentsRect":{"y":0,"x":0,"width":1,"height":1},"opacity":1,"edgeAntialiasingMask":0,"height":768,"hidden":false,"anchorPoint":{"pointX":0.5,"pointY":0.5}},"objectID":"0","layers":[{"animations":[],"initialState":{"affineTransform":[1,0,0,1,0,0],"masksToBounds":false,"rotation":0,"scale":1,"position":{"pointX":512,"pointY":384},"width":1024,"sublayerTransform":[1,0,0,0,0,1,0,0,0,0,1,-0.0004922987690640373,0,0,0,1],"contentsRect":{"y":0,"x":0,"width":1,"height":1},"opacity":1,"edgeAntialiasingMask":15,"height":768,"hidden":false,"anchorPoint":{"pointX":0.5,"pointY":0.5}},"layers":[{"animations":[],"layers":[],"initialState":{"affineTransform":[1,0,0,1,0,0],"masksToBounds":false,"rotation":0,"scale":1,"position":{"pointX":512,"pointY":384},"width":1024,"sublayerTransform":[1,0,0,0,0,1,0,0,0,0,1,0,0,0,0,1],"contentsRect":{"y":0,"x":0,"width":1,"height":1},"opacity":1,"edgeAntialiasingMask":0,"height":768,"hidden":false,"anchorPoint":{"pointX":0.5,"pointY":0.5}},"texture":"3F31FB1C6482085783ED237C5946F3B3"}]}]}}},"targetRectangle":{"y":29.28194808959961,"x":44.89100646972656,"width":57.47475051879883,"height":59.15297698974609}}],"accessibility":[{"text":"1-08.png","targetRectangle":{"y":0,"x":0,"width":1024,"height":768}},{"text":"Je hebt een BLIJE diamant!","targetRectangle":{"y":655.0360107421875,"x":290.0039100646973,"width":443.9921875,"height":41}},{"text":"2.png","targetRectangle":{"y":222.232177734375,"x":420.4095687866211,"width":183.1808929443359,"height":180.0043640136719}}],"baseLayer":{"animations":[],"initialState":{"affineTransform":[1,0,0,1,0,0],"masksToBounds":true,"rotation":0,"scale":1,"position":{"pointX":512,"pointY":384},"width":1024,"sublayerTransform":[1,0,0,0,0,1,0,0,0,0,1,0,0,0,0,1],"contentsRect":{"y":0,"x":0,"width":1,"height":1},"opacity":1,"edgeAntialiasingMask":0,"height":768,"hidden":false,"anchorPoint":{"pointX":0.5,"pointY":0.5}},"layers":[{"animations":[],"initialState":{"affineTransform":[1,0,0,1,0,0],"masksToBounds":false,"rotation":0,"scale":1,"position":{"pointX":512,"pointY":384},"width":1024,"sublayerTransform":[1,0,0,0,0,1,0,0,0,0,1,0,0,0,0,1],"contentsRect":{"y":0,"x":0,"width":1,"height":1},"opacity":1,"edgeAntialiasingMask":15,"height":768,"hidden":false,"anchorPoint":{"pointX":0.5,"pointY":0.5}},"layers":[{"animations":[],"initialState":{"affineTransform":[1,0,0,1,0,0],"masksToBounds":false,"rotation":0,"scale":1,"position":{"pointX":512,"pointY":384},"width":1024,"sublayerTransform":[1,0,0,0,0,1,0,0,0,0,1,0,0,0,0,1],"contentsRect":{"y":0,"x":0,"width":1,"height":1},"opacity":1,"edgeAntialiasingMask":15,"height":768,"hidden":false,"anchorPoint":{"pointX":0.5,"pointY":0.5}},"layers":[{"animations":[],"layers":[],"initialState":{"affineTransform":[1,0,0,1,0,0],"masksToBounds":false,"rotation":0,"scale":1,"position":{"pointX":512,"pointY":384},"width":1024,"sublayerTransform":[1,0,0,0,0,1,0,0,0,0,1,0,0,0,0,1],"contentsRect":{"y":0,"x":0,"width":1,"height":1},"opacity":1,"edgeAntialiasingMask":0,"height":768,"hidden":false,"anchorPoint":{"pointX":0.5,"pointY":0.5}},"texture":"BB5CB91ED7406511BDB06F3E85F7244F"}]}]},{"animations":[],"initialState":{"affineTransform":[1,0,0,1,0,0],"masksToBounds":false,"rotation":0,"scale":1,"position":{"pointX":512,"pointY":384},"width":1024,"sublayerTransform":[1,0,0,0,0,1,0,0,0,0,1,0,0,0,0,1],"contentsRect":{"y":0,"x":0,"width":1,"height":1},"opacity":1,"edgeAntialiasingMask":15,"height":768,"hidden":false,"anchorPoint":{"pointX":0.5,"pointY":0.5}},"layers":[{"animations":[],"initialState":{"affineTransform":[1,0,0,1,0,0],"masksToBounds":false,"rotation":0,"scale":1,"position":{"pointX":512,"pointY":384},"width":1024,"sublayerTransform":[1,0,0,0,0,1,0,0,0,0,1,0,0,0,0,1],"contentsRect":{"y":0,"x":0,"width":1,"height":1},"opacity":1,"edgeAntialiasingMask":15,"height":768,"hidden":false,"anchorPoint":{"pointX":0.5,"pointY":0.5}},"objectID":"191680C0-7BD4-437F-9F4C-0DEBB09E4A2F","layers":[{"animations":[],"layers":[],"initialState":{"affineTransform":[1,0,0,1,0,0],"masksToBounds":false,"rotation":0,"scale":1,"position":{"pointX":512,"pointY":384},"width":1026,"sublayerTransform":[1,0,0,0,0,1,0,0,0,0,1,0,0,0,0,1],"contentsRect":{"y":0,"x":0,"width":1,"height":1},"opacity":1,"edgeAntialiasingMask":0,"height":770,"hidden":false,"anchorPoint":{"pointX":0.5,"pointY":0.5}},"texture":"FA4CF99553AC39E60FF2C938B73757CC"}]}]},{"animations":[],"initialState":{"affineTransform":[1,0,0,1,0,0],"masksToBounds":false,"rotation":0,"scale":1,"position":{"pointX":512,"pointY":384},"width":1024,"sublayerTransform":[1,0,0,0,0,1,0,0,0,0,1,0,0,0,0,1],"contentsRect":{"y":0,"x":0,"width":1,"height":1},"opacity":1,"edgeAntialiasingMask":15,"height":768,"hidden":false,"anchorPoint":{"pointX":0.5,"pointY":0.5}},"layers":[{"animations":[],"initialState":{"affineTransform":[1,0,0,1,0,0],"masksToBounds":false,"rotation":0,"scale":1,"position":{"pointX":512,"pointY":675.1380624771118},"width":1024.000053405762,"sublayerTransform":[1,0,0,0,0,1,0,0,0,0,1,0,0,0,0,1],"contentsRect":{"y":0,"x":0,"width":1,"height":1},"opacity":1,"edgeAntialiasingMask":15,"height":187.2041034698486,"hidden":false,"anchorPoint":{"pointX":0.5,"pointY":0.5}},"objectID":"290507FF-22CC-4532-B63D-175C50B232C2","layers":[{"animations":[],"layers":[],"initialState":{"affineTransform":[1,0,0,1,0,0],"masksToBounds":false,"rotation":0,"scale":1,"position":{"pointX":512.0000267028809,"pointY":93.4639892578125},"width":1028,"sublayerTransform":[1,0,0,0,0,1,0,0,0,0,1,0,0,0,0,1],"contentsRect":{"y":0,"x":0,"width":1,"height":1},"opacity":1,"edgeAntialiasingMask":0,"height":190,"hidden":false,"anchorPoint":{"pointX":0.5,"pointY":0.5}},"texture":"8F6820361D2B1BCD4C02FD502FE51D8F"}]}]},{"animations":[],"initialState":{"affineTransform":[1,0,0,1,0,0],"masksToBounds":false,"rotation":0,"scale":1,"position":{"pointX":512,"pointY":384},"width":1024,"sublayerTransform":[1,0,0,0,0,1,0,0,0,0,1,0,0,0,0,1],"contentsRect":{"y":0,"x":0,"width":1,"height":1},"opacity":1,"edgeAntialiasingMask":15,"height":768,"hidden":false,"anchorPoint":{"pointX":0.5,"pointY":0.5}},"layers":[{"animations":[],"initialState":{"affineTransform":[1,0,0,1,0,0],"masksToBounds":false,"rotation":0,"scale":1,"position":{"pointX":512.0000152587891,"pointY":310.2343597412109},"width":356.3009338378906,"sublayerTransform":[1,0,0,0,0,1,0,0,0,0,1,0,0,0,0,1],"contentsRect":{"y":0,"x":0,"width":1,"height":1},"opacity":1,"edgeAntialiasingMask":15,"height":356.3009338378906,"hidden":false,"anchorPoint":{"pointX":0.5,"pointY":0.5}},"objectID":"97EDECDC-5164-4331-8E0F-AB7BB4666B34","layers":[{"animations":[],"layers":[],"initialState":{"affineTransform":[1,0,0,1,0,0],"masksToBounds":false,"rotation":0,"scale":1,"position":{"pointX":178.1504669189453,"pointY":178.1504669189453},"width":372,"sublayerTransform":[1,0,0,0,0,1,0,0,0,0,1,0,0,0,0,1],"contentsRect":{"y":0,"x":0,"width":1,"height":1},"opacity":1,"edgeAntialiasingMask":0,"height":371,"hidden":false,"anchorPoint":{"pointX":0.5000000410182501,"pointY":0.4992839885207842}},"texture":"8A2C835FC8BD9D135CD739D6C99EC526"}]}]},{"animations":[],"initialState":{"affineTransform":[1,0,0,1,0,0],"masksToBounds":false,"rotation":0,"scale":1,"position":{"pointX":512,"pointY":384},"width":1024,"sublayerTransform":[1,0,0,0,0,1,0,0,0,0,1,0,0,0,0,1],"contentsRect":{"y":0,"x":0,"width":1,"height":1},"opacity":1,"edgeAntialiasingMask":15,"height":768,"hidden":false,"anchorPoint":{"pointX":0.5,"pointY":0.5}},"layers":[{"animations":[],"initialState":{"affineTransform":[1,0,0,1,0,0],"masksToBounds":false,"rotation":0,"scale":1,"position":{"pointX":73.62838172912598,"pointY":58.85843658447266},"width":57.47475051879883,"sublayerTransform":[1,0,0,0,0,1,0,0,0,0,1,0,0,0,0,1],"contentsRect":{"y":0,"x":0,"width":1,"height":1},"opacity":1,"edgeAntialiasingMask":15,"height":59.15297698974609,"hidden":false,"anchorPoint":{"pointX":0.5,"pointY":0.5}},"objectID":"BFAA546A-4FD4-4F18-9998-E4E1BC24FD3E","layers":[{"animations":[],"layers":[],"initialState":{"affineTransform":[1,0,0,1,0,0],"masksToBounds":false,"rotation":0,"scale":1,"position":{"pointX":28.60899353027344,"pointY":29.71805191040039},"width":67,"sublayerTransform":[1,0,0,0,0,1,0,0,0,0,1,0,0,0,0,1],"contentsRect":{"y":0,"x":0,"width":1,"height":1},"opacity":1,"edgeAntialiasingMask":0,"height":72,"hidden":false,"anchorPoint":{"pointX":0.5,"pointY":0.5}},"texture":"D7668D704E27AC9557F646207BF431C4"}]}]}]}},{"effects":[{"beginTime":0,"baseLayer":{"animations":[],"initialState":{"affineTransform":[1,0,0,1,0,0],"masksToBounds":true,"rotation":0,"scale":1,"position":{"pointX":512,"pointY":384},"width":1024,"sublayerTransform":[1,0,0,0,0,1,0,0,0,0,1,0,0,0,0,1],"contentsRect":{"y":0,"x":0,"width":1,"height":1},"opacity":1,"edgeAntialiasingMask":0,"height":768,"hidden":false,"anchorPoint":{"pointX":0.5,"pointY":0.5}},"objectID":"0","layers":[{"animations":[],"initialState":{"affineTransform":[1,0,0,1,0,0],"masksToBounds":false,"rotation":0,"scale":1,"position":{"pointX":512,"pointY":384},"width":1024,"sublayerTransform":[1,0,0,0,0,1,0,0,0,0,1,-0.0004922987690640373,0,0,0,1],"contentsRect":{"y":0,"x":0,"width":1,"height":1},"opacity":1,"edgeAntialiasingMask":15,"height":768,"hidden":false,"anchorPoint":{"pointX":0.5,"pointY":0.5}},"layers":[{"animations":[],"layers":[],"initialState":{"affineTransform":[1,0,0,1,0,0],"masksToBounds":false,"rotation":0,"scale":1,"position":{"pointX":512,"pointY":384},"width":1024,"sublayerTransform":[1,0,0,0,0,1,0,0,0,0,1,0,0,0,0,1],"contentsRect":{"y":0,"x":0,"width":1,"height":1},"opacity":1,"edgeAntialiasingMask":0,"height":768,"hidden":false,"anchorPoint":{"pointX":0.5,"pointY":0.5}},"texture":"57BFB1565B11D17E0D5A3302F4E76C9B"},{"animations":[{"from":{"scalar":false},"beginTime":0,"repeatCount":0,"fillMode":"both","property":"hidden","duration":0.01,"to":{"scalar":true}}],"layers":[],"initialState":{"affineTransform":[1,0,0,1,0,0],"masksToBounds":false,"rotation":0,"scale":1,"position":{"pointX":512,"pointY":384},"width":1024,"sublayerTransform":[1,0,0,0,0,1,0,0,0,0,1,0,0,0,0,1],"contentsRect":{"y":0,"x":0,"width":1,"height":1},"opacity":1,"edgeAntialiasingMask":0,"height":768,"hidden":false,"anchorPoint":{"pointX":0.5,"pointY":0.5}},"texture":"3F31FB1C6482085783ED237C5946F3B3"}]}]},"effects":[],"duration":0.01,"type":"transition","name":"none","objectID":"0"}],"automaticPlay":false,"hyperlinks":[{"url":"?slide=next","events":{"556F520D-83B4-4A3D-A31F-A820DC724E09":{"effects":[{"beginTime":0,"baseLayer":{"animations":[],"initialState":{"affineTransform":[1,0,0,1,0,0],"masksToBounds":true,"rotation":0,"scale":1,"position":{"pointX":512,"pointY":384},"width":1024,"sublayerTransform":[1,0,0,0,0,1,0,0,0,0,1,0,0,0,0,1],"contentsRect":{"y":0,"x":0,"width":1,"height":1},"opacity":1,"edgeAntialiasingMask":0,"height":768,"hidden":false,"anchorPoint":{"pointX":0.5,"pointY":0.5}},"objectID":"0","layers":[{"animations":[],"initialState":{"affineTransform":[1,0,0,1,0,0],"masksToBounds":false,"rotation":0,"scale":1,"position":{"pointX":512,"pointY":384},"width":1024,"sublayerTransform":[1,0,0,0,0,1,0,0,0,0,1,-0.0004922987690640373,0,0,0,1],"contentsRect":{"y":0,"x":0,"width":1,"height":1},"opacity":1,"edgeAntialiasingMask":15,"height":768,"hidden":false,"anchorPoint":{"pointX":0.5,"pointY":0.5}},"layers":[{"animations":[],"layers":[],"initialState":{"affineTransform":[1,0,0,1,0,0],"masksToBounds":false,"rotation":0,"scale":1,"position":{"pointX":512,"pointY":384},"width":1024,"sublayerTransform":[1,0,0,0,0,1,0,0,0,0,1,0,0,0,0,1],"contentsRect":{"y":0,"x":0,"width":1,"height":1},"opacity":1,"edgeAntialiasingMask":0,"height":768,"hidden":false,"anchorPoint":{"pointX":0.5,"pointY":0.5}},"texture":"57BFB1565B11D17E0D5A3302F4E76C9B"},{"animations":[{"from":{"scalar":false},"beginTime":0,"repeatCount":0,"fillMode":"both","property":"hidden","duration":0.01,"to":{"scalar":true}}],"layers":[],"initialState":{"affineTransform":[1,0,0,1,0,0],"masksToBounds":false,"rotation":0,"scale":1,"position":{"pointX":512,"pointY":384},"width":1024,"sublayerTransform":[1,0,0,0,0,1,0,0,0,0,1,0,0,0,0,1],"contentsRect":{"y":0,"x":0,"width":1,"height":1},"opacity":1,"edgeAntialiasingMask":0,"height":768,"hidden":false,"anchorPoint":{"pointX":0.5,"pointY":0.5}},"texture":"3F31FB1C6482085783ED237C5946F3B3"}]}]},"effects":[],"duration":0.01,"type":"transition","name":"none","objectID":"0"}],"automaticPlay":false,"hyperlinks":[],"accessibility":[],"baseLayer":{"animations":[],"initialState":{"affineTransform":[1,0,0,1,0,0],"masksToBounds":true,"rotation":0,"scale":1,"position":{"pointX":512,"pointY":384},"width":1024,"sublayerTransform":[1,0,0,0,0,1,0,0,0,0,1,0,0,0,0,1],"contentsRect":{"y":0,"x":0,"width":1,"height":1},"opacity":1,"edgeAntialiasingMask":0,"height":768,"hidden":false,"anchorPoint":{"pointX":0.5,"pointY":0.5}},"objectID":"0","layers":[{"animations":[],"initialState":{"affineTransform":[1,0,0,1,0,0],"masksToBounds":false,"rotation":0,"scale":1,"position":{"pointX":512,"pointY":384},"width":1024,"sublayerTransform":[1,0,0,0,0,1,0,0,0,0,1,-0.0004922987690640373,0,0,0,1],"contentsRect":{"y":0,"x":0,"width":1,"height":1},"opacity":1,"edgeAntialiasingMask":15,"height":768,"hidden":false,"anchorPoint":{"pointX":0.5,"pointY":0.5}},"layers":[{"animations":[],"layers":[],"initialState":{"affineTransform":[1,0,0,1,0,0],"masksToBounds":false,"rotation":0,"scale":1,"position":{"pointX":512,"pointY":384},"width":1024,"sublayerTransform":[1,0,0,0,0,1,0,0,0,0,1,0,0,0,0,1],"contentsRect":{"y":0,"x":0,"width":1,"height":1},"opacity":1,"edgeAntialiasingMask":0,"height":768,"hidden":false,"anchorPoint":{"pointX":0.5,"pointY":0.5}},"texture":"3F31FB1C6482085783ED237C5946F3B3"}]}]}}},"targetRectangle":{"y":29.28194808959961,"x":44.89100646972656,"width":57.47475051879883,"height":59.15297698974609}}],"accessibility":[{"text":"1-08.png","targetRectangle":{"y":0,"x":0,"width":1024,"height":768}},{"text":"Je hebt een BLIJE diamant!","targetRectangle":{"y":655.0360107421875,"x":290.0039100646973,"width":443.9921875,"height":41}},{"text":"2.png","targetRectangle":{"y":222.232177734375,"x":420.4095687866211,"width":183.1808929443359,"height":180.0043640136719}}],"baseLayer":{"animations":[],"initialState":{"affineTransform":[1,0,0,1,0,0],"masksToBounds":true,"rotation":0,"scale":1,"position":{"pointX":512,"pointY":384},"width":1024,"sublayerTransform":[1,0,0,0,0,1,0,0,0,0,1,0,0,0,0,1],"contentsRect":{"y":0,"x":0,"width":1,"height":1},"opacity":1,"edgeAntialiasingMask":0,"height":768,"hidden":false,"anchorPoint":{"pointX":0.5,"pointY":0.5}},"objectID":"0","layers":[{"animations":[],"initialState":{"affineTransform":[1,0,0,1,0,0],"masksToBounds":false,"rotation":0,"scale":1,"position":{"pointX":512,"pointY":384},"width":1024,"sublayerTransform":[1,0,0,0,0,1,0,0,0,0,1,-0.0004922987690640373,0,0,0,1],"contentsRect":{"y":0,"x":0,"width":1,"height":1},"opacity":1,"edgeAntialiasingMask":15,"height":768,"hidden":false,"anchorPoint":{"pointX":0.5,"pointY":0.5}},"layers":[{"animations":[],"layers":[],"initialState":{"affineTransform":[1,0,0,1,0,0],"masksToBounds":false,"rotation":0,"scale":1,"position":{"pointX":512,"pointY":384},"width":1024,"sublayerTransform":[1,0,0,0,0,1,0,0,0,0,1,0,0,0,0,1],"contentsRect":{"y":0,"x":0,"width":1,"height":1},"opacity":1,"edgeAntialiasingMask":0,"height":768,"hidden":false,"anchorPoint":{"pointX":0.5,"pointY":0.5}},"texture":"3F31FB1C6482085783ED237C5946F3B3"}]}]}}]}